winfetch.py
winfetch_py-1.0.5.dist-info/LICENSE
winfetch_py-1.0.5.dist-info/METADATA
winfetch_py-1.0.5.dist-info/WHEEL
winfetch_py-1.0.5.dist-info/top_level.txt
winfetch_py-1.0.5.dist-info/RECORD
