Metadata-Version: 2.1
Name: winfetch-py
Version: 1.0.5
Summary: An original neofetch clone for windows built in python that aims to be as simple as possible.
Author: Warrobot10
Project-URL: Homepage, https://github.com/Warrobot10/winfetch-py
Project-URL: Issues, https://github.com/Warrobot10/winfetch-py
Classifier: Programming Language :: Python :: 3
Requires-Python: >=3.10
License-File: LICENSE
